Metadata-Version: 2.1
Name: readbinary
Version: 1.0.0
Summary: A Python module for defining and executing functions using binary strings
Home-page: https://github.com/developerlaborotory/readbinary
Author: Dev Lab
Author-email: sa021w@hotmail.com
